SingleEndpointRouter/__init__.py
SingleEndpointRouter/server.py
single_endpoint_router-1.0.1.dist-info/LICENSE
single_endpoint_router-1.0.1.dist-info/METADATA
single_endpoint_router-1.0.1.dist-info/WHEEL
single_endpoint_router-1.0.1.dist-info/RECORD
